{
  "source_name": "zenodo",
  "source_id": "10692439",
  "source_url": "https://zenodo.org/records/10692439",
  "doi": "10.5281/zenodo.10692439",
  "title": "ISOLATION OF NATURAL DYE FROM CODIAEUM VARIEGATUM",
  "author": "Khalida Tasneem",
  "license": "cc-by-4.0",
  "license_verified": true,
  "license_note": "Zenodo record metadata license field: cc-by-4.0",
  "description": "Abstract    \n   &nbsp;&nbsp;&nbsp;&nbsp;&nbsp;&nbsp;&nbsp;&nbsp;&nbsp;&nbsp;&nbsp;&nbsp;&nbsp;&nbsp;&nbsp;&nbsp;&nbsp;&nbsp;&nbsp;&nbsp;&nbsp;&nbsp;&nbsp;&nbsp;  The powdered dried leaves of Codiaeum Variegatum &ldquo; garden croton&rdquo; or Variegated croton&rdquo; refluxed &nbsp;  with alcohol for 12 hours. Natural dye obtained was then applied on wool using different mordants gave beautiful parrot green, light green, light brown and dark brown shades.  \n   &nbsp; Codiaeum Variegatum is a species of plant in the genus Codiaeum, which is a member  \n   &nbsp; Of the family Euphorbiaceae. It is native to southern India, Sri Lanka, Indonesia, Malaysia and the Western Pacific Ocean islands, growing in open forests and scrub. It is an evergreen shrub growing to 3m tall and has large, thick, leathery , shiny evergreen leaves, alternately arranged, 30 cm long and 0.5-8 cm broad.  \n   &nbsp;  Preparation of Natural Dye and its application on wool with different mordants :-  \n   &nbsp;&nbsp;&nbsp;&nbsp;  The macerated leaves of Codiaeum Variegatum was refluxed with alcohol for 12 hours ,filtered and the solvent was evaporated in rotator apparatus under reduced pressure, the solid residue obtained as natural dye was treated with wool with 10% and 20% of mordants copper sulphate, Ferrous sulphate and potassium dichromate. Boiling wool with natural dye and mordant for one hour. Washing of dyed wool with water &nbsp;  and than drying in shade at room temperature. In all cases same timing and same procedure was applied. Mordanting helps the dye bind to the fibre. Different mordants allow different colour ranges for each dyestuff.  \n   &nbsp;  The amount of mordant used was a percentage of the weight of fibre.It was important to note the different in shades when the wool was first mordanting then dyeing, than the colour of wool first dyeing then mordanting.Also the shades changes with the increase in the percentage of modants taking the percentage of dye same. There was also change in shades when first dyeing &nbsp;  and than mordanting.   \n  Key words: Codiaeum Variegatum, dye,",
  "steps_raw": "Abstract    \n   &nbsp;&nbsp;&nbsp;&nbsp;&nbsp;&nbsp;&nbsp;&nbsp;&nbsp;&nbsp;&nbsp;&nbsp;&nbsp;&nbsp;&nbsp;&nbsp;&nbsp;&nbsp;&nbsp;&nbsp;&nbsp;&nbsp;&nbsp;&nbsp;  The powdered dried leaves of Codiaeum Variegatum &ldquo; garden croton&rdquo; or Variegated croton&rdquo; refluxed &nbsp;  with alcohol for 12 hours. Natural dye obtained was then applied on wool using different mordants gave beautiful parrot green, light green, light brown and dark brown shades.  \n   &nbsp; Codiaeum Variegatum is a species of plant in the genus Codiaeum, which is a member  \n   &nbsp; Of the family Euphorbiaceae. It is native to southern India, Sri Lanka, Indonesia, Malaysia and the Western Pacific Ocean islands, growing in open forests and scrub. It is an evergreen shrub growing to 3m tall and has large, thick, leathery , shiny evergreen leaves, alternately arranged, 30 cm long and 0.5-8 cm broad.  \n   &nbsp;  Preparation of Natural Dye and its application on wool with different mordants :-  \n   &nbsp;&nbsp;&nbsp;&nbsp;  The macerated leaves of Codiaeum Variegatum was refluxed with alcohol for 12 hours ,filtered and the solvent was evaporated in rotator apparatus under reduced pressure, the solid residue obtained as natural dye was treated with wool with 10% and 20% of mordants copper sulphate, Ferrous sulphate and potassium dichromate. Boiling wool with natural dye and mordant for one hour. Washing of dyed wool with water &nbsp;  and than drying in shade at room temperature. In all cases same timing and same procedure was applied. Mordanting helps the dye bind to the fibre. Different mordants allow different colour ranges for each dyestuff.  \n   &nbsp;  The amount of mordant used was a percentage of the weight of fibre.It was important to note the different in shades when the wool was first mordanting then dyeing, than the colour of wool first dyeing then mordanting.Also the shades changes with the increase in the percentage of modants taking the percentage of dye same. There was also change in shades when first dyeing &nbsp;  and than mordanting.   \n  Key words: Codiaeum Variegatum, dye,",
  "keywords": [
    "Codiaeum Variegatum",
    "dye"
  ],
  "resource_type": "publication",
  "fetched_at": "2026-06-18T20:09:47.587627"
}