{
  "source_name": "zenodo",
  "source_id": "12752127",
  "source_url": "https://zenodo.org/records/12752127",
  "doi": "10.1117/1.NPh.9.4.041410",
  "title": "Semi-automated Pipeline for Optical ATP Sensors",
  "author": "HASHEMIAGHDAM, ARSALAN",
  "license": "cc-by-4.0",
  "license_verified": true,
  "license_note": "Zenodo record metadata license field: cc-by-4.0",
  "description": "Significance: &nbsp;The firefly enzyme luciferase has been used in a wide range of biological assays, including bioluminescence imaging of adenosine triphosphate (ATP). The biosensor Syn-ATP utilizes subcellular targeting of luciferase to nerve terminals for optical measurement of ATP in this compartment. Manual analysis of Syn-ATP signals is challenging due to signal heterogeneity and cellular motion in long imaging sessions. Here, we have leveraged machine learning tools to develop a method for analysis of bioluminescence images.&nbsp; Aim: &nbsp;Our goal was to create a semiautomated pipeline for analysis of bioluminescence imaging to improve measurements of ATP content in nerve terminals.&nbsp; Approach: &nbsp;We developed an image analysis pipeline that applies machine learning toolkits to distinguish neurons from background signals and excludes neural cell bodies, while also incorporating user input.&nbsp; Results: &nbsp;Side-by-side comparison of manual and semiautomated image analysis demonstrated that the latter improves precision and accuracy of ATP measurements.&nbsp; Conclusions:  Our method streamlines data analysis and reduces user-introduced bias, thus enhancing the reproducibility and reliability of quantitative ATP imaging in nerve terminals.",
  "steps_raw": "Significance: &nbsp;The firefly enzyme luciferase has been used in a wide range of biological assays, including bioluminescence imaging of adenosine triphosphate (ATP). The biosensor Syn-ATP utilizes subcellular targeting of luciferase to nerve terminals for optical measurement of ATP in this compartment. Manual analysis of Syn-ATP signals is challenging due to signal heterogeneity and cellular motion in long imaging sessions. Here, we have leveraged machine learning tools to develop a method for analysis of bioluminescence images.&nbsp; Aim: &nbsp;Our goal was to create a semiautomated pipeline for analysis of bioluminescence imaging to improve measurements of ATP content in nerve terminals.&nbsp; Approach: &nbsp;We developed an image analysis pipeline that applies machine learning toolkits to distinguish neurons from background signals and excludes neural cell bodies, while also incorporating user input.&nbsp; Results: &nbsp;Side-by-side comparison of manual and semiautomated image analysis demonstrated that the latter improves precision and accuracy of ATP measurements.&nbsp; Conclusions:  Our method streamlines data analysis and reduces user-introduced bias, thus enhancing the reproducibility and reliability of quantitative ATP imaging in nerve terminals.",
  "keywords": [],
  "resource_type": "software",
  "fetched_at": "2026-06-18T19:30:54.750745"
}