{
  "source_name": "zenodo",
  "source_id": "17349050",
  "source_url": "https://zenodo.org/records/17349050",
  "doi": "10.5281/zenodo.17349050",
  "title": "Assessing viral pollution in coastal environments, using passive samplers, quantitative PCR and target enrichment sequencing",
  "author": "Estarlich-Landajo, Ignasi",
  "license": "cc-by-4.0",
  "license_verified": true,
  "license_note": "Zenodo record metadata license field: cc-by-4.0",
  "description": "",
  "steps_raw": "",
  "keywords": [],
  "resource_type": "dataset",
  "fetched_at": "2026-06-18T19:19:57.232349"
}