{
  "source_name": "zenodo",
  "source_id": "3570318",
  "source_url": "https://zenodo.org/records/3570318",
  "doi": "10.31142/ijtsrd7085",
  "title": "A Review on Detection of Plant Diseases using Image Processing Technique",
  "author": "Ms. Shweta R. Astonkar",
  "license": "cc-by-4.0",
  "license_verified": true,
  "license_note": "Zenodo record metadata license field: cc-by-4.0",
  "description": "Identification of the plant diseases is the key topreventing the losses in the yield and quantity of the agricultural product. The studies of the plant diseases mean the studies of visually observable patterns seen on the plant. Health monitoring and disease detection on plant is very critical for sustainable agriculture. It is very difficult to monitor the plant diseases manually requires tremendous amount of work, expertize in the plant diseases, and also require the excessive processing time. Hence, image processing is used for the detection of plant diseases. Disease detection involves the steps like image segmentation, feature extraction and classification. This paper discussed the method used for the detection of plant diseases using their leaves images. Agriculture is a most important and ancient occupation in India. As economy of India is based on agricultural production, utmost care of food production is necessary. Pests like virus, fungus and bacteria causes infection to plants with loss in quality and quantity production. There is large amount of loss of farmer in production. Hence proper care of plants is necessary for same. Ms. Shweta R. Astonkar | Prof. V. K. Shandilya &quot;A Review on Detection of Plant Diseases using Image Processing Technique&quot; Published in International Journal of Trend in Scientific Research and Development (ijtsrd), ISSN: 2456-6470, Volume-2 | Issue-1 , December 2017, URL: https://www.ijtsrd.com/papers/ijtsrd7085.pdf",
  "steps_raw": "Identification of the plant diseases is the key topreventing the losses in the yield and quantity of the agricultural product. The studies of the plant diseases mean the studies of visually observable patterns seen on the plant. Health monitoring and disease detection on plant is very critical for sustainable agriculture. It is very difficult to monitor the plant diseases manually requires tremendous amount of work, expertize in the plant diseases, and also require the excessive processing time. Hence, image processing is used for the detection of plant diseases. Disease detection involves the steps like image segmentation, feature extraction and classification. This paper discussed the method used for the detection of plant diseases using their leaves images. Agriculture is a most important and ancient occupation in India. As economy of India is based on agricultural production, utmost care of food production is necessary. Pests like virus, fungus and bacteria causes infection to plants with loss in quality and quantity production. There is large amount of loss of farmer in production. Hence proper care of plants is necessary for same. Ms. Shweta R. Astonkar | Prof. V. K. Shandilya &quot;A Review on Detection of Plant Diseases using Image Processing Technique&quot; Published in International Journal of Trend in Scientific Research and Development (ijtsrd), ISSN: 2456-6470, Volume-2 | Issue-1 , December 2017, URL: https://www.ijtsrd.com/papers/ijtsrd7085.pdf",
  "keywords": [
    "Computer Engineering",
    "Image processing",
    "Plant Diseases",
    "Agriculture"
  ],
  "resource_type": "publication",
  "fetched_at": "2026-06-18T20:09:47.587942"
}