{
  "source_name": "zenodo",
  "source_id": "47591",
  "source_url": "https://zenodo.org/records/47591",
  "doi": "10.19070/2326-3350- 1400028",
  "title": "Folin-Ciocalteau Reagent for Polyphenolic Assay",
  "author": "Gabriel A Agbor",
  "license": "cc-by-4.0",
  "license_verified": true,
  "license_note": "Zenodo record metadata license field: cc-by-4.0",
  "description": "The chemistry of the Folin-Ciocalteu is described and two Folin assays (single and dual reagent) are described for the assay of phenols and&nbsp;polyphenols with respect to experimental detail and critically evaluated for pure compounds and for mixtures (plant extracts). The single reagent&nbsp;method was found to be more precise and sensitive. The problem of interferences in the Folin assay was&nbsp;evaluated for both methods.&nbsp;Interferences for the dual reagent methodology can be eliminated by a solid phase removal of phenols using a commercial resin (Oasys HLB)&nbsp;or polyvinylpyrrolidone resin (Polyclar AT). A new basic/acid hydrolysis combed with the Polyclar AT was used to measure the total phenols \nin a sample as previous methods measured only the phenolic groups not bound as ether or ester groups. A semi-automated method, microplate&nbsp;reader, is described as to the experimental procedure and applicability. Miscellaneous uses of the Folin assay including flow injection,urine&nbsp;analysis and a mixed standard are briefly described.",
  "steps_raw": "The chemistry of the Folin-Ciocalteu is described and two Folin assays (single and dual reagent) are described for the assay of phenols and&nbsp;polyphenols with respect to experimental detail and critically evaluated for pure compounds and for mixtures (plant extracts). The single reagent&nbsp;method was found to be more precise and sensitive. The problem of interferences in the Folin assay was&nbsp;evaluated for both methods.&nbsp;Interferences for the dual reagent methodology can be eliminated by a solid phase removal of phenols using a commercial resin (Oasys HLB)&nbsp;or polyvinylpyrrolidone resin (Polyclar AT). A new basic/acid hydrolysis combed with the Polyclar AT was used to measure the total phenols \nin a sample as previous methods measured only the phenolic groups not bound as ether or ester groups. A semi-automated method, microplate&nbsp;reader, is described as to the experimental procedure and applicability. Miscellaneous uses of the Folin assay including flow injection,urine&nbsp;analysis and a mixed standard are briefly described.",
  "keywords": [
    "Phenol",
    "Folin-Cocialteu reagent",
    "solid phase extraction"
  ],
  "resource_type": "publication",
  "fetched_at": "2026-06-18T18:37:47.538919"
}