{
  "source_name": "zenodo",
  "source_id": "5877236",
  "source_url": "https://zenodo.org/records/5877236",
  "doi": "10.5281/zenodo.5877236",
  "title": "Knowledge management opportunities at Meili",
  "author": "Wilkinson, Laura J.",
  "license": "cc-by-4.0",
  "license_verified": true,
  "license_note": "Zenodo record metadata license field: cc-by-4.0",
  "description": "Report of a knowledge management opportunities research project carried out at a French tech start-up in January 2022. \n\n The report examines the quantitative and qualitative data I obtained from my study, makes recommendations for what we should stop, keep, and start doing across different areas of our work, and concludes with next steps to kick off the action phase.",
  "steps_raw": "Report of a knowledge management opportunities research project carried out at a French tech start-up in January 2022. \n\n The report examines the quantitative and qualitative data I obtained from my study, makes recommendations for what we should stop, keep, and start doing across different areas of our work, and concludes with next steps to kick off the action phase.",
  "keywords": [
    "Knowledge management",
    "Start-ups",
    "Small organizations",
    "Information management",
    "Working practices",
    "Remote working"
  ],
  "resource_type": "publication",
  "fetched_at": "2026-06-18T19:20:42.700152"
}