{
  "source_name": "zenodo",
  "source_id": "6592289",
  "source_url": "https://zenodo.org/records/6592289",
  "doi": "10.5281/zenodo.6592289",
  "title": "ACTION OF p-TOLUENE-SULPHONYL CHLORIDE ON POLYNITRO-OXY- DIPHENYLS",
  "author": "A. B. SEN",
  "license": "cc-by-4.0",
  "license_verified": true,
  "license_note": "Zenodo record metadata license field: cc-by-4.0",
  "description": "The action of  p -toluene-salphonyl chloride on 3 : 5-dinitro-4-oxydiphenyl and 3 :5  : 4&#39;-trinitro -4-oxydiphenyl has been examined. \n\n In each case&nbsp;a chloro&nbsp;compound has been obtained in the presence of diethylaniline as the condens&shy;ing reagent. 3 : 5-Dinitro-4-oxydiphenyl forms also a  p -toluene-sulphonite in the presence of sodium carbonate as the condensing reagent. \n\n The action of various amines and amino compounds on&nbsp;these chloro compounds has also been studied.",
  "steps_raw": "The action of  p -toluene-salphonyl chloride on 3 : 5-dinitro-4-oxydiphenyl and 3 :5  : 4&#39;-trinitro -4-oxydiphenyl has been examined. \n\n In each case&nbsp;a chloro&nbsp;compound has been obtained in the presence of diethylaniline as the condens&shy;ing reagent. 3 : 5-Dinitro-4-oxydiphenyl forms also a  p -toluene-sulphonite in the presence of sodium carbonate as the condensing reagent. \n\n The action of various amines and amino compounds on&nbsp;these chloro compounds has also been studied.",
  "keywords": [
    "Sodium",
    "Amino compounds"
  ],
  "resource_type": "publication",
  "fetched_at": "2026-06-18T19:01:16.736264"
}