{
  "source_name": "github_opentrons",
  "source_id": "eaf0d9aa070c",
  "source_url": "https://github.com/Opentrons/Protocols/tree/main/protocols/010d6c",
  "doi": "",
  "title": "Ribogreen Assay",
  "author": "Opentrons",
  "license": "Apache-2.0",
  "license_verified": true,
  "license_note": "GitHub repo Opentrons/Protocols — Apache-2.0",
  "description": "This protocol performs a Ribrogreen assay - for detailed protocol steps, please see below. There is the option to perform duplicate/triplicate plating. The csv for sample input should include `source slot, source well, destination well` in the header.",
  "steps_raw": [
    "This protocol performs a Ribrogreen assay - for detailed protocol steps, please see below. There is the option to perform duplicate/triplicate plating. The csv for sample input should include `source slot, source well, destination well` in the header.",
    "Calibration standard preparation in deep well plate (matrix buffer addition)",
    "Calibration standard preparation in deep well plate (4 ug/mL calibration stock addition)",
    "Calibration standard plating (duplicate or triplicate)",
    "Sample plating (duplicate or triplicate)",
    "Triton addition",
    "TE addition",
    "Heating at 37 C for 10 minutes",
    "Dye addition"
  ],
  "keywords": [
    "Sample Prep",
    "Plate Filling"
  ],
  "materials_raw": [
    "Corning 12 Reservoir 2000 µL",
    "Nunc 96 Well Plate 400 µL",
    "Opentrons 15 Tube Rack with eppendorf 5 mL",
    "Pyramid 96 Well Plate 2000 µL",
    "Opentrons 96 Tip Rack 300 µL",
    "Opentrons 24 Tube Rack with NEST 2 mL Snapcap",
    "Opentrons P300 Single Channel Electronic Pipette (GEN2)",
    "Opentrons P300 8 Channel Electronic Pipette (GEN2)"
  ],
  "resource_type": "protocol",
  "fetched_at": "2026-06-18T19:35:17.290163+00:00"
}